prueba/__init__.py
prueba/modulo.py
example_pkg_alejandro050995-0.0.1.dist-info/LICENSE
example_pkg_alejandro050995-0.0.1.dist-info/METADATA
example_pkg_alejandro050995-0.0.1.dist-info/WHEEL
example_pkg_alejandro050995-0.0.1.dist-info/top_level.txt
example_pkg_alejandro050995-0.0.1.dist-info/RECORD
